MLAstra/Classfication.py
MLAstra/Functional.py
MLAstra/__init__.py
MLAstra-0.0.1.dist-info/LICENSE
MLAstra-0.0.1.dist-info/METADATA
MLAstra-0.0.1.dist-info/WHEEL
MLAstra-0.0.1.dist-info/top_level.txt
MLAstra-0.0.1.dist-info/RECORD
