Metadata-Version: 2.1
Name: MLAstra
Version: 0.0.1
Summary: Machine Learning and Deep Learning Models
Home-page: UNKNOWN
Author: Shashikant
Author-email: <shashikantprasad1111@gmail.com>
License: UNKNOWN
Platform: UNKNOWN
Classifier: Development Status :: 1 - Planning
Classifier: Intended Audience :: Developers
Classifier: Programming Language :: Python :: 3
Classifier: Operating System :: Unix
Classifier: Operating System :: MacOS :: MacOS X
Classifier: Operating System :: Microsoft :: Windows
License-File: LICENSE
Requires-Dist: numpy
